[{
    "key": "group_599eaa60c0e79",
    "title": "Section base fields",
    "fields": [
        {
            "key": "field_599eaa6a6c354",
            "label": "Content",
            "name": "mod_section_content",
            "type": "wysiwyg",
            "instructions": "",
            "required": 0,
            "conditional_logic": 0,
            "wrapper": {
                "width": "",
                "class": "",
                "id": ""
            },
            "default_value": "",
            "tabs": "all",
            "toolbar": "full",
            "media_upload": 1,
            "delay": 0
        },
        {
            "key": "field_599eab01559ea",
            "label": "Section Height",
            "name": "mod_section_height",
            "type": "radio",
            "instructions": "Select the amount of space that the section should take up vertically",
            "required": 1,
            "conditional_logic": 0,
            "wrapper": {
                "width": "",
                "class": "",
                "id": ""
            },
            "choices": {
                "sm": "Small (Adapt to content)",
                "md": "Medium (Minimum 40 % height)",
                "lg": "Large (Minimum 100% height)"
            },
            "allow_null": 0,
            "other_choice": 0,
            "save_other_choice": 0,
            "default_value": "",
            "layout": "horizontal",
            "return_format": "value"
        },
        {
            "key": "field_599eabaeaad08",
            "label": "Background focus (vertical)",
            "name": "mod_section_bg_position_vertical",
            "type": "radio",
            "instructions": "If the image has to be cropped to fit the view, where is the background focal point vertically?",
            "required": 1,
            "conditional_logic": 0,
            "wrapper": {
                "width": "",
                "class": "",
                "id": ""
            },
            "choices": {
                "top": "Top",
                "center": "Middle",
                "bottom": "Bottom"
            },
            "allow_null": 0,
            "other_choice": 0,
            "save_other_choice": 0,
            "default_value": "center",
            "layout": "horizontal",
            "return_format": "value"
        },
        {
            "key": "field_599eac93ead36",
            "label": "Background focus (horizontal)",
            "name": "mod_section_bg_position_horizontal",
            "type": "radio",
            "instructions": "If the image has to be cropped to fit the view, where is the background focal point horizontally?",
            "required": 1,
            "conditional_logic": 0,
            "wrapper": {
                "width": "",
                "class": "",
                "id": ""
            },
            "choices": {
                "left": "Left",
                "center": "Center",
                "bottom": "Right"
            },
            "allow_null": 0,
            "other_choice": 0,
            "save_other_choice": 0,
            "default_value": "center",
            "layout": "horizontal",
            "return_format": "value"
        },
        {
            "key": "field_599eaf20c6db6",
            "label": "Effects",
            "name": "mod_section_effect",
            "type": "checkbox",
            "instructions": "",
            "required": 0,
            "conditional_logic": 0,
            "wrapper": {
                "width": "",
                "class": "",
                "id": ""
            },
            "choices": {
                "multiply": "Multiply - Blend the background image with the background color to make the background image more coherence to your overall profile.",
                "parallax": "Parallax - Create some depth with a fixed background in the section. This option creates a illusion that indicates that the content floats on-top of the background."
            },
            "allow_custom": 0,
            "save_custom": 0,
            "default_value": [],
            "layout": "vertical",
            "toggle": 0,
            "return_format": "value"
        },
        {
            "key": "field_599ec93c4b4b7",
            "label": "Image position",
            "name": "mod_section_image_position",
            "type": "radio",
            "instructions": "Select on what side of the screen that the image should be placed.",
            "required": 0,
            "conditional_logic": 0,
            "wrapper": {
                "width": "",
                "class": "",
                "id": ""
            },
            "choices": {
                "left": "Left",
                "right": "Right"
            },
            "allow_null": 0,
            "other_choice": 0,
            "save_other_choice": 0,
            "default_value": "left",
            "layout": "horizontal",
            "return_format": "value"
        },
        {
            "key": "field_599ecb18ef407",
            "label": "Content position",
            "name": "mod_section_content_position",
            "type": "radio",
            "instructions": "",
            "required": 0,
            "conditional_logic": 0,
            "wrapper": {
                "width": "",
                "class": "",
                "id": ""
            },
            "choices": {
                "top": "Top",
                "middle": "Middle",
                "bottom": "Bottom"
            },
            "allow_null": 0,
            "other_choice": 0,
            "save_other_choice": 0,
            "default_value": "",
            "layout": "horizontal",
            "return_format": "value"
        },
        {
            "key": "field_599ecc223a4f6",
            "label": "Section margin",
            "name": "mod_section_padding",
            "type": "radio",
            "instructions": "",
            "required": 0,
            "conditional_logic": 0,
            "wrapper": {
                "width": "",
                "class": "",
                "id": ""
            },
            "choices": {
                "sm": "Small",
                "md": "Medium",
                "lg": "Large"
            },
            "allow_null": 0,
            "other_choice": 0,
            "save_other_choice": 0,
            "default_value": "",
            "layout": "horizontal",
            "return_format": "value"
        }
    ],
    "location": [
        [
            {
                "param": "post_type",
                "operator": "==",
                "value": "post"
            }
        ]
    ],
    "menu_order": 0,
    "position": "normal",
    "style": "default",
    "label_placement": "top",
    "instruction_placement": "label",
    "hide_on_screen": "",
    "active": 1,
    "description": ""
}]
